{
  "swagger" : "2.0",
  "info" : {
    "description" : "RESTful API文档",
    "version" : "v1.0",
    "title" : "RESTful API文档",
    "termsOfService" : "http://www.showtime.com/",
    "contact" : {
      "name" : "showtime",
      "url" : "http://www.showtime.com",
      "email" : "594470882@qq.com"
    }
  },
  "basePath" : "/rs",
  "tags" : [ {
    "name" : "上传模块"
  }, {
    "name" : "变动接口"
  }, {
    "name" : "后台管理权限接口"
  }, {
    "name" : "后台管理用户接口"
  }, {
    "name" : "后台管理角色接口"
  }, {
    "name" : "后缀生成接口"
  }, {
    "name" : "奖学金接口"
  }, {
    "name" : "学生接口"
  }, {
    "name" : "性别接口"
  }, {
    "name" : "成绩接口"
  }, {
    "name" : "班级接口"
  }, {
    "name" : "课程平均成绩接口"
  }, {
    "name" : "课程接口"
  } ],
  "schemes" : [ "http", "https" ],
  "paths" : {
    "/api/v1/avgfractions" : {
      "get" : {
        "tags" : [ "课程平均成绩接口" ],
        "summary" : "获取课程平均成绩列表",
        "description" : "通过查询条件获取课程平均成绩列表",
        "operationId" : "getAvgFractions",
        "produces" : [ "application/json;charset=UTF-8" ],
        "parameters" : [ {
          "name" : "courseNumber",
          "in" : "query",
          "description" : "课程编号",
          "required" : false,
          "type" : "string"
        }, {
          "name" : "avgFraction",
          "in" : "query",
          "description" : "平均成绩",
          "required" : false,
          "type" : "number"
        }, {
          "name" : "pageNumber",
          "in" : "query",
          "description" : "页数",
          "required" : false,
          "type" : "integer",
          "default" : 0,
          "format" : "int32"
        }, {
          "name" : "pageSize",
          "in" : "query",
          "description" : "每页加载量",
          "required" : false,
          "type" : "integer",
          "default" : 10,
          "format" : "int32"
        } ],
        "responses" : {
          "200" : {
            "description" : "successful request"
          },
          "500" : {
            "description" : "internal server error"
          }
        }
      },
      "post" : {
        "tags" : [ "课程平均成绩接口" ],
        "summary" : "创建课程平均成绩",
        "description" : "创建一个课程平均成绩",
        "operationId" : "createAvgFraction",
        "produces" : [ "application/json;charset=UTF-8" ],
        "parameters" : [ {
          "in" : "body",
          "name" : "body",
          "description" : "课程平均成绩",
          "required" : true,
          "schema" : {
            "$ref" : "#/definitions/AvgFractionView"
          }
        } ],
        "responses" : {
          "201" : {
            "description" : "successful operation",
            "headers" : {
              "location" : {
                "type" : "string",
                "description" : "URL of new created resource"
              }
            }
          },
          "409" : {
            "description" : "conflict"
          },
          "500" : {
            "description" : "internal server error"
          }
        }
      },
      "delete" : {
        "tags" : [ "课程平均成绩接口" ],
        "summary" : "删除课程平均成绩",
        "description" : "批量删除课程平均成绩",
        "operationId" : "deleteAvgFractions",
        "produces" : [ "application/json;charset=UTF-8" ],
        "parameters" : [ {
          "in" : "body",
          "name" : "body",
          "description" : "课程平均成绩ids，样例 - 1,2,3",
          "required" : true,
          "schema" : {
            "type" : "string"
          }
        } ],
        "responses" : {
          "200" : {
            "description" : "successful request"
          },
          "500" : {
            "description" : "internal server error"
          }
        }
      }
    },
    "/api/v1/avgfractions/search" : {
      "get" : {
        "tags" : [ "课程平均成绩接口" ],
        "summary" : "通过关键字搜索课程平均成绩",
        "description" : "通过关键字搜索课程平均成绩",
        "operationId" : "getAvgFractionByKeyword",
        "produces" : [ "application/json;charset=UTF-8" ],
        "parameters" : [ {
          "name" : "keyword",
          "in" : "query",
          "description" : "关键字",
          "required" : true,
          "type" : "string"
        }, {
          "name" : "pageNumber",
          "in" : "query",
          "description" : "页数",
          "required" : false,
          "type" : "integer",
          "default" : 0,
          "format" : "int32"
        }, {
          "name" : "pageSize",
          "in" : "query",
          "description" : "每页加载量",
          "required" : false,
          "type" : "integer",
          "default" : 10,
          "format" : "int32"
        } ],
        "responses" : {
          "200" : {
            "description" : "successful request"
          },
          "500" : {
            "description" : "internal server error"
          }
        }
      }
    },
    "/api/v1/avgfractions/{id}" : {
      "get" : {
        "tags" : [ "课程平均成绩接口" ],
        "summary" : "获取单个课程平均成绩",
        "description" : "通过id获取课程平均成绩",
        "operationId" : "getAvgFraction",
        "produces" : [ "application/json;charset=UTF-8" ],
        "parameters" : [ {
          "name" : "id",
          "in" : "path",
          "description" : "课程平均成绩id",
          "required" : true,
          "type" : "integer",
          "format" : "int64"
        } ],
        "responses" : {
          "200" : {
            "description" : "successful request"
          },
          "500" : {
            "description" : "internal server error"
          }
        }
      },
      "put" : {
        "tags" : [ "课程平均成绩接口" ],
        "summary" : "更新课程平均成绩",
        "description" : "更新课程平均成绩信息",
        "operationId" : "updateAvgFractions",
        "produces" : [ "application/json;charset=UTF-8" ],
        "parameters" : [ {
          "name" : "id",
          "in" : "path",
          "description" : "课程平均成绩id",
          "required" : true,
          "type" : "integer",
          "format" : "int64"
        }, {
          "in" : "body",
          "name" : "body",
          "description" : "课程平均成绩信息",
          "required" : true,
          "schema" : {
            "$ref" : "#/definitions/AvgFractionView"
          }
        } ],
        "responses" : {
          "200" : {
            "description" : "successful"
          },
          "404" : {
            "description" : "not found"
          },
          "409" : {
            "description" : "conflict"
          },
          "500" : {
            "description" : "internal Server Error"
          }
        }
      },
      "delete" : {
        "tags" : [ "课程平均成绩接口" ],
        "summary" : "删除课程平均成绩",
        "description" : "通过id删除课程平均成绩",
        "operationId" : "deleteAvgFraction",
        "produces" : [ "application/json;charset=UTF-8" ],
        "parameters" : [ {
          "name" : "id",
          "in" : "path",
          "description" : "课程平均成绩id",
          "required" : true,
          "type" : "integer",
          "format" : "int64"
        } ],
        "responses" : {
          "200" : {
            "description" : "successful request"
          },
          "500" : {
            "description" : "internal server error"
          }
        }
      }
    },
    "/api/v1/changes" : {
      "get" : {
        "tags" : [ "变动接口" ],
        "summary" : "获取变动列表",
        "description" : "通过查询条件获取变动列表",
        "operationId" : "getChanges",
        "produces" : [ "application/json;charset=UTF-8" ],
        "parameters" : [ {
          "name" : "changeName",
          "in" : "query",
          "description" : "变动",
          "required" : false,
          "type" : "string"
        }, {
          "name" : "isChange",
          "in" : "query",
          "description" : "0-未变动 1-已变动",
          "required" : false,
          "type" : "string"
        }, {
          "name" : "pageNumber",
          "in" : "query",
          "description" : "页数",
          "required" : false,
          "type" : "integer",
          "default" : 0,
          "format" : "int32"
        }, {
          "name" : "pageSize",
          "in" : "query",
          "description" : "每页加载量",
          "required" : false,
          "type" : "integer",
          "default" : 10,
          "format" : "int32"
        } ],
        "responses" : {
          "200" : {
            "description" : "successful request"
          },
          "500" : {
            "description" : "internal server error"
          }
        }
      },
      "post" : {
        "tags" : [ "变动接口" ],
        "summary" : "创建变动",
        "description" : "创建一个变动",
        "operationId" : "createChange",
        "produces" : [ "application/json;charset=UTF-8" ],
        "parameters" : [ {
          "in" : "body",
          "name" : "body",
          "description" : "变动",
          "required" : true,
          "schema" : {
            "$ref" : "#/definitions/ChangeView"
          }
        } ],
        "responses" : {
          "201" : {
            "description" : "successful operation",
            "headers" : {
              "location" : {
                "type" : "string",
                "description" : "URL of new created resource"
              }
            }
          },
          "409" : {
            "description" : "conflict"
          },
          "500" : {
            "description" : "internal server error"
          }
        }
      },
      "delete" : {
        "tags" : [ "变动接口" ],
        "summary" : "删除变动",
        "description" : "批量删除变动",
        "operationId" : "deleteChanges",
        "produces" : [ "application/json;charset=UTF-8" ],
        "parameters" : [ {
          "in" : "body",
          "name" : "body",
          "description" : "变动ids，样例 - 1,2,3",
          "required" : true,
          "schema" : {
            "type" : "string"
          }
        } ],
        "responses" : {
          "200" : {
            "description" : "successful request"
          },
          "500" : {
            "description" : "internal server error"
          }
        }
      }
    },
    "/api/v1/changes/search" : {
      "get" : {
        "tags" : [ "变动接口" ],
        "summary" : "通过关键字搜索变动",
        "description" : "通过关键字搜索变动",
        "operationId" : "getChangeByKeyword",
        "produces" : [ "application/json;charset=UTF-8" ],
        "parameters" : [ {
          "name" : "keyword",
          "in" : "query",
          "description" : "关键字",
          "required" : true,
          "type" : "string"
        }, {
          "name" : "pageNumber",
          "in" : "query",
          "description" : "页数",
          "required" : false,
          "type" : "integer",
          "default" : 0,
          "format" : "int32"
        }, {
          "name" : "pageSize",
          "in" : "query",
          "description" : "每页加载量",
          "required" : false,
          "type" : "integer",
          "default" : 10,
          "format" : "int32"
        } ],
        "responses" : {
          "200" : {
            "description" : "successful request"
          },
          "500" : {
            "description" : "internal server error"
          }
        }
      }
    },
    "/api/v1/changes/{id}" : {
      "get" : {
        "tags" : [ "变动接口" ],
        "summary" : "获取单个变动",
        "description" : "通过id获取变动",
        "operationId" : "getChange",
        "produces" : [ "application/json;charset=UTF-8" ],
        "parameters" : [ {
          "name" : "id",
          "in" : "path",
          "description" : "变动id",
          "required" : true,
          "type" : "integer",
          "format" : "int64"
        } ],
        "responses" : {
          "200" : {
            "description" : "successful request"
          },
          "500" : {
            "description" : "internal server error"
          }
        }
      },
      "put" : {
        "tags" : [ "变动接口" ],
        "summary" : "更新变动",
        "description" : "更新变动信息",
        "operationId" : "updateChanges",
        "produces" : [ "application/json;charset=UTF-8" ],
        "parameters" : [ {
          "name" : "id",
          "in" : "path",
          "description" : "变动id",
          "required" : true,
          "type" : "integer",
          "format" : "int64"
        }, {
          "in" : "body",
          "name" : "body",
          "description" : "变动信息",
          "required" : true,
          "schema" : {
            "$ref" : "#/definitions/ChangeView"
          }
        } ],
        "responses" : {
          "200" : {
            "description" : "successful"
          },
          "404" : {
            "description" : "not found"
          },
          "409" : {
            "description" : "conflict"
          },
          "500" : {
            "description" : "internal Server Error"
          }
        }
      },
      "delete" : {
        "tags" : [ "变动接口" ],
        "summary" : "删除变动",
        "description" : "通过id删除变动",
        "operationId" : "deleteChange",
        "produces" : [ "application/json;charset=UTF-8" ],
        "parameters" : [ {
          "name" : "id",
          "in" : "path",
          "description" : "变动id",
          "required" : true,
          "type" : "integer",
          "format" : "int64"
        } ],
        "responses" : {
          "200" : {
            "description" : "successful request"
          },
          "500" : {
            "description" : "internal server error"
          }
        }
      }
    },
    "/api/v1/classnames" : {
      "get" : {
        "tags" : [ "班级接口" ],
        "summary" : "获取班级列表",
        "description" : "通过查询条件获取班级列表",
        "operationId" : "getClassNames",
        "produces" : [ "application/json;charset=UTF-8" ],
        "parameters" : [ {
          "name" : "grade",
          "in" : "query",
          "description" : "年级",
          "required" : false,
          "type" : "string"
        }, {
          "name" : "className",
          "in" : "query",
          "description" : "班级名称",
          "required" : false,
          "type" : "string"
        }, {
          "name" : "pageNumber",
          "in" : "query",
          "description" : "页数",
          "required" : false,
          "type" : "integer",
          "default" : 0,
          "format" : "int32"
        }, {
          "name" : "pageSize",
          "in" : "query",
          "description" : "每页加载量",
          "required" : false,
          "type" : "integer",
          "default" : 10,
          "format" : "int32"
        } ],
        "responses" : {
          "200" : {
            "description" : "successful request"
          },
          "500" : {
            "description" : "internal server error"
          }
        }
      },
      "post" : {
        "tags" : [ "班级接口" ],
        "summary" : "创建班级",
        "description" : "创建一个班级",
        "operationId" : "createClassName",
        "produces" : [ "application/json;charset=UTF-8" ],
        "parameters" : [ {
          "in" : "body",
          "name" : "body",
          "description" : "班级",
          "required" : true,
          "schema" : {
            "$ref" : "#/definitions/ClassNameView"
          }
        } ],
        "responses" : {
          "201" : {
            "description" : "successful operation",
            "headers" : {
              "location" : {
                "type" : "string",
                "description" : "URL of new created resource"
              }
            }
          },
          "409" : {
            "description" : "conflict"
          },
          "500" : {
            "description" : "internal server error"
          }
        }
      },
      "delete" : {
        "tags" : [ "班级接口" ],
        "summary" : "删除班级",
        "description" : "批量删除班级",
        "operationId" : "deleteClassNames",
        "produces" : [ "application/json;charset=UTF-8" ],
        "parameters" : [ {
          "in" : "body",
          "name" : "body",
          "description" : "班级ids，样例 - 1,2,3",
          "required" : true,
          "schema" : {
            "type" : "string"
          }
        } ],
        "responses" : {
          "200" : {
            "description" : "successful request"
          },
          "500" : {
            "description" : "internal server error"
          }
        }
      }
    },
    "/api/v1/classnames/search" : {
      "get" : {
        "tags" : [ "班级接口" ],
        "summary" : "通过关键字搜索班级",
        "description" : "通过关键字搜索班级",
        "operationId" : "getClassNameByKeyword",
        "produces" : [ "application/json;charset=UTF-8" ],
        "parameters" : [ {
          "name" : "keyword",
          "in" : "query",
          "description" : "关键字",
          "required" : true,
          "type" : "string"
        }, {
          "name" : "pageNumber",
          "in" : "query",
          "description" : "页数",
          "required" : false,
          "type" : "integer",
          "default" : 0,
          "format" : "int32"
        }, {
          "name" : "pageSize",
          "in" : "query",
          "description" : "每页加载量",
          "required" : false,
          "type" : "integer",
          "default" : 10,
          "format" : "int32"
        } ],
        "responses" : {
          "200" : {
            "description" : "successful request"
          },
          "500" : {
            "description" : "internal server error"
          }
        }
      }
    },
    "/api/v1/classnames/{id}" : {
      "get" : {
        "tags" : [ "班级接口" ],
        "summary" : "获取单个班级",
        "description" : "通过id获取班级",
        "operationId" : "getClassName",
        "produces" : [ "application/json;charset=UTF-8" ],
        "parameters" : [ {
          "name" : "id",
          "in" : "path",
          "description" : "班级id",
          "required" : true,
          "type" : "integer",
          "format" : "int64"
        } ],
        "responses" : {
          "200" : {
            "description" : "successful request"
          },
          "500" : {
            "description" : "internal server error"
          }
        }
      },
      "put" : {
        "tags" : [ "班级接口" ],
        "summary" : "更新班级",
        "description" : "更新班级信息",
        "operationId" : "updateClassNames",
        "produces" : [ "application/json;charset=UTF-8" ],
        "parameters" : [ {
          "name" : "id",
          "in" : "path",
          "description" : "班级id",
          "required" : true,
          "type" : "integer",
          "format" : "int64"
        }, {
          "in" : "body",
          "name" : "body",
          "description" : "班级信息",
          "required" : true,
          "schema" : {
            "$ref" : "#/definitions/ClassNameView"
          }
        } ],
        "responses" : {
          "200" : {
            "description" : "successful"
          },
          "404" : {
            "description" : "not found"
          },
          "409" : {
            "description" : "conflict"
          },
          "500" : {
            "description" : "internal Server Error"
          }
        }
      },
      "delete" : {
        "tags" : [ "班级接口" ],
        "summary" : "删除班级",
        "description" : "通过id删除班级",
        "operationId" : "deleteClassName",
        "produces" : [ "application/json;charset=UTF-8" ],
        "parameters" : [ {
          "name" : "id",
          "in" : "path",
          "description" : "班级id",
          "required" : true,
          "type" : "integer",
          "format" : "int64"
        } ],
        "responses" : {
          "200" : {
            "description" : "successful request"
          },
          "500" : {
            "description" : "internal server error"
          }
        }
      }
    },
    "/api/v1/courses" : {
      "get" : {
        "tags" : [ "课程接口" ],
        "summary" : "获取课程列表",
        "description" : "通过查询条件获取课程列表",
        "operationId" : "getCourses",
        "produces" : [ "application/json;charset=UTF-8" ],
        "parameters" : [ {
          "name" : "courseNumber",
          "in" : "query",
          "description" : "课程编号",
          "required" : false,
          "type" : "string"
        }, {
          "name" : "name",
          "in" : "query",
          "description" : "课程名称",
          "required" : false,
          "type" : "string"
        }, {
          "name" : "learnHours",
          "in" : "query",
          "description" : "学时",
          "required" : false,
          "type" : "string"
        }, {
          "name" : "credit",
          "in" : "query",
          "description" : "学分",
          "required" : false,
          "type" : "string"
        }, {
          "name" : "avgFraction",
          "in" : "query",
          "description" : "平均分",
          "required" : false,
          "type" : "number"
        }, {
          "name" : "preCourse",
          "in" : "query",
          "description" : "先修课id号",
          "required" : false,
          "type" : "integer",
          "format" : "int64"
        }, {
          "name" : "pageNumber",
          "in" : "query",
          "description" : "页数",
          "required" : false,
          "type" : "integer",
          "default" : 0,
          "format" : "int32"
        }, {
          "name" : "pageSize",
          "in" : "query",
          "description" : "每页加载量",
          "required" : false,
          "type" : "integer",
          "default" : 10,
          "format" : "int32"
        } ],
        "responses" : {
          "200" : {
            "description" : "successful request"
          },
          "500" : {
            "description" : "internal server error"
          }
        }
      },
      "post" : {
        "tags" : [ "课程接口" ],
        "summary" : "创建课程",
        "description" : "创建一个课程",
        "operationId" : "createCourse",
        "produces" : [ "application/json;charset=UTF-8" ],
        "parameters" : [ {
          "in" : "body",
          "name" : "body",
          "description" : "课程",
          "required" : true,
          "schema" : {
            "$ref" : "#/definitions/CourseView"
          }
        } ],
        "responses" : {
          "201" : {
            "description" : "successful operation",
            "headers" : {
              "location" : {
                "type" : "string",
                "description" : "URL of new created resource"
              }
            }
          },
          "409" : {
            "description" : "conflict"
          },
          "500" : {
            "description" : "internal server error"
          }
        }
      },
      "delete" : {
        "tags" : [ "课程接口" ],
        "summary" : "删除课程",
        "description" : "批量删除课程",
        "operationId" : "deleteCourses",
        "produces" : [ "application/json;charset=UTF-8" ],
        "parameters" : [ {
          "in" : "body",
          "name" : "body",
          "description" : "课程ids，样例 - 1,2,3",
          "required" : true,
          "schema" : {
            "type" : "string"
          }
        } ],
        "responses" : {
          "200" : {
            "description" : "successful request"
          },
          "500" : {
            "description" : "internal server error"
          }
        }
      }
    },
    "/api/v1/courses/avgFraction" : {
      "put" : {
        "tags" : [ "课程接口" ],
        "summary" : "更新课程平均成绩",
        "description" : "更新课程平均成绩",
        "operationId" : "updateCoursesAvgFraction",
        "produces" : [ "application/json;charset=UTF-8" ],
        "responses" : {
          "200" : {
            "description" : "successful"
          },
          "404" : {
            "description" : "not found"
          },
          "409" : {
            "description" : "conflict"
          },
          "500" : {
            "description" : "internal Server Error"
          }
        }
      }
    },
    "/api/v1/courses/preCourses/all" : {
      "get" : {
        "tags" : [ "课程接口" ],
        "summary" : "获取课程列表",
        "description" : "通过查询条件获取课程列表",
        "operationId" : "getAllPreCourses",
        "produces" : [ "application/json;charset=UTF-8" ],
        "responses" : {
          "200" : {
            "description" : "successful request"
          },
          "500" : {
            "description" : "internal server error"
          }
        }
      }
    },
    "/api/v1/courses/search" : {
      "get" : {
        "tags" : [ "课程接口" ],
        "summary" : "通过关键字搜索课程",
        "description" : "通过关键字搜索课程",
        "operationId" : "getCourseByKeyword",
        "produces" : [ "application/json;charset=UTF-8" ],
        "parameters" : [ {
          "name" : "keyword",
          "in" : "query",
          "description" : "关键字",
          "required" : true,
          "type" : "string"
        }, {
          "name" : "pageNumber",
          "in" : "query",
          "description" : "页数",
          "required" : false,
          "type" : "integer",
          "default" : 0,
          "format" : "int32"
        }, {
          "name" : "pageSize",
          "in" : "query",
          "description" : "每页加载量",
          "required" : false,
          "type" : "integer",
          "default" : 10,
          "format" : "int32"
        } ],
        "responses" : {
          "200" : {
            "description" : "successful request"
          },
          "500" : {
            "description" : "internal server error"
          }
        }
      }
    },
    "/api/v1/courses/{id}" : {
      "get" : {
        "tags" : [ "课程接口" ],
        "summary" : "获取单个课程",
        "description" : "通过id获取课程",
        "operationId" : "getCourse",
        "produces" : [ "application/json;charset=UTF-8" ],
        "parameters" : [ {
          "name" : "id",
          "in" : "path",
          "description" : "课程id",
          "required" : true,
          "type" : "integer",
          "format" : "int64"
        } ],
        "responses" : {
          "200" : {
            "description" : "successful request"
          },
          "500" : {
            "description" : "internal server error"
          }
        }
      },
      "put" : {
        "tags" : [ "课程接口" ],
        "summary" : "更新课程",
        "description" : "更新课程信息",
        "operationId" : "updateCourses",
        "produces" : [ "application/json;charset=UTF-8" ],
        "parameters" : [ {
          "name" : "id",
          "in" : "path",
          "description" : "课程id",
          "required" : true,
          "type" : "integer",
          "format" : "int64"
        }, {
          "in" : "body",
          "name" : "body",
          "description" : "课程信息",
          "required" : true,
          "schema" : {
            "$ref" : "#/definitions/CourseView"
          }
        } ],
        "responses" : {
          "200" : {
            "description" : "successful"
          },
          "404" : {
            "description" : "not found"
          },
          "409" : {
            "description" : "conflict"
          },
          "500" : {
            "description" : "internal Server Error"
          }
        }
      },
      "delete" : {
        "tags" : [ "课程接口" ],
        "summary" : "删除课程",
        "description" : "通过id删除课程",
        "operationId" : "deleteCourse",
        "produces" : [ "application/json;charset=UTF-8" ],
        "parameters" : [ {
          "name" : "id",
          "in" : "path",
          "description" : "课程id",
          "required" : true,
          "type" : "integer",
          "format" : "int64"
        } ],
        "responses" : {
          "200" : {
            "description" : "successful request"
          },
          "500" : {
            "description" : "internal server error"
          }
        }
      }
    },
    "/api/v1/genders" : {
      "get" : {
        "tags" : [ "性别接口" ],
        "summary" : "获取性别列表",
        "description" : "通过查询条件获取性别列表",
        "operationId" : "getGenders",
        "produces" : [ "application/json;charset=UTF-8" ],
        "parameters" : [ {
          "name" : "gender",
          "in" : "query",
          "description" : "性别",
          "required" : false,
          "type" : "string"
        }, {
          "name" : "pageNumber",
          "in" : "query",
          "description" : "页数",
          "required" : false,
          "type" : "integer",
          "default" : 0,
          "format" : "int32"
        }, {
          "name" : "pageSize",
          "in" : "query",
          "description" : "每页加载量",
          "required" : false,
          "type" : "integer",
          "default" : 10,
          "format" : "int32"
        } ],
        "responses" : {
          "200" : {
            "description" : "successful request"
          },
          "500" : {
            "description" : "internal server error"
          }
        }
      },
      "post" : {
        "tags" : [ "性别接口" ],
        "summary" : "创建性别",
        "description" : "创建一个性别",
        "operationId" : "createGender",
        "produces" : [ "application/json;charset=UTF-8" ],
        "parameters" : [ {
          "in" : "body",
          "name" : "body",
          "description" : "性别",
          "required" : true,
          "schema" : {
            "$ref" : "#/definitions/GenderView"
          }
        } ],
        "responses" : {
          "201" : {
            "description" : "successful operation",
            "headers" : {
              "location" : {
                "type" : "string",
                "description" : "URL of new created resource"
              }
            }
          },
          "409" : {
            "description" : "conflict"
          },
          "500" : {
            "description" : "internal server error"
          }
        }
      },
      "delete" : {
        "tags" : [ "性别接口" ],
        "summary" : "删除性别",
        "description" : "批量删除性别",
        "operationId" : "deleteGenders",
        "produces" : [ "application/json;charset=UTF-8" ],
        "parameters" : [ {
          "in" : "body",
          "name" : "body",
          "description" : "性别ids，样例 - 1,2,3",
          "required" : true,
          "schema" : {
            "type" : "string"
          }
        } ],
        "responses" : {
          "200" : {
            "description" : "successful request"
          },
          "500" : {
            "description" : "internal server error"
          }
        }
      }
    },
    "/api/v1/genders/search" : {
      "get" : {
        "tags" : [ "性别接口" ],
        "summary" : "通过关键字搜索性别",
        "description" : "通过关键字搜索性别",
        "operationId" : "getGenderByKeyword",
        "produces" : [ "application/json;charset=UTF-8" ],
        "parameters" : [ {
          "name" : "keyword",
          "in" : "query",
          "description" : "关键字",
          "required" : true,
          "type" : "string"
        }, {
          "name" : "pageNumber",
          "in" : "query",
          "description" : "页数",
          "required" : false,
          "type" : "integer",
          "default" : 0,
          "format" : "int32"
        }, {
          "name" : "pageSize",
          "in" : "query",
          "description" : "每页加载量",
          "required" : false,
          "type" : "integer",
          "default" : 10,
          "format" : "int32"
        } ],
        "responses" : {
          "200" : {
            "description" : "successful request"
          },
          "500" : {
            "description" : "internal server error"
          }
        }
      }
    },
    "/api/v1/genders/{id}" : {
      "get" : {
        "tags" : [ "性别接口" ],
        "summary" : "获取单个性别",
        "description" : "通过id获取性别",
        "operationId" : "getGender",
        "produces" : [ "application/json;charset=UTF-8" ],
        "parameters" : [ {
          "name" : "id",
          "in" : "path",
          "description" : "性别id",
          "required" : true,
          "type" : "integer",
          "format" : "int64"
        } ],
        "responses" : {
          "200" : {
            "description" : "successful request"
          },
          "500" : {
            "description" : "internal server error"
          }
        }
      },
      "put" : {
        "tags" : [ "性别接口" ],
        "summary" : "更新性别",
        "description" : "更新性别信息",
        "operationId" : "updateGenders",
        "produces" : [ "application/json;charset=UTF-8" ],
        "parameters" : [ {
          "name" : "id",
          "in" : "path",
          "description" : "性别id",
          "required" : true,
          "type" : "integer",
          "format" : "int64"
        }, {
          "in" : "body",
          "name" : "body",
          "description" : "性别信息",
          "required" : true,
          "schema" : {
            "$ref" : "#/definitions/GenderView"
          }
        } ],
        "responses" : {
          "200" : {
            "description" : "successful"
          },
          "404" : {
            "description" : "not found"
          },
          "409" : {
            "description" : "conflict"
          },
          "500" : {
            "description" : "internal Server Error"
          }
        }
      },
      "delete" : {
        "tags" : [ "性别接口" ],
        "summary" : "删除性别",
        "description" : "通过id删除性别",
        "operationId" : "deleteGender",
        "produces" : [ "application/json;charset=UTF-8" ],
        "parameters" : [ {
          "name" : "id",
          "in" : "path",
          "description" : "性别id",
          "required" : true,
          "type" : "integer",
          "format" : "int64"
        } ],
        "responses" : {
          "200" : {
            "description" : "successful request"
          },
          "500" : {
            "description" : "internal server error"
          }
        }
      }
    },
    "/api/v1/generators" : {
      "get" : {
        "tags" : [ "后缀生成接口" ],
        "summary" : "获取后缀生成列表",
        "description" : "通过查询条件获取后缀生成列表",
        "operationId" : "getGenerators",
        "produces" : [ "application/json;charset=UTF-8" ],
        "parameters" : [ {
          "name" : "enabled",
          "in" : "query",
          "description" : "状态",
          "required" : false,
          "type" : "integer",
          "format" : "int32"
        }, {
          "name" : "pageNumber",
          "in" : "query",
          "description" : "页数",
          "required" : false,
          "type" : "integer",
          "default" : 0,
          "format" : "int32"
        }, {
          "name" : "pageSize",
          "in" : "query",
          "description" : "每页加载量",
          "required" : false,
          "type" : "integer",
          "default" : 10,
          "format" : "int32"
        } ],
        "responses" : {
          "200" : {
            "description" : "successful request"
          },
          "500" : {
            "description" : "internal server error"
          }
        }
      },
      "post" : {
        "tags" : [ "后缀生成接口" ],
        "summary" : "创建后缀生成",
        "description" : "创建一个后缀生成",
        "operationId" : "createGenerator",
        "produces" : [ "application/json;charset=UTF-8" ],
        "parameters" : [ {
          "in" : "body",
          "name" : "body",
          "description" : "后缀生成",
          "required" : true,
          "schema" : {
            "$ref" : "#/definitions/GeneratorView"
          }
        } ],
        "responses" : {
          "201" : {
            "description" : "successful operation",
            "headers" : {
              "location" : {
                "type" : "string",
                "description" : "URL of new created resource"
              }
            }
          },
          "409" : {
            "description" : "conflict"
          },
          "500" : {
            "description" : "internal server error"
          }
        }
      },
      "delete" : {
        "tags" : [ "后缀生成接口" ],
        "summary" : "删除后缀生成",
        "description" : "批量删除后缀生成",
        "operationId" : "deleteGenerators",
        "produces" : [ "application/json;charset=UTF-8" ],
        "parameters" : [ {
          "in" : "body",
          "name" : "body",
          "description" : "后缀生成ids，样例 - 1,2,3",
          "required" : true,
          "schema" : {
            "type" : "string"
          }
        } ],
        "responses" : {
          "200" : {
            "description" : "successful request"
          },
          "500" : {
            "description" : "internal server error"
          }
        }
      }
    },
    "/api/v1/generators/{id}" : {
      "get" : {
        "tags" : [ "后缀生成接口" ],
        "summary" : "获取单个后缀生成",
        "description" : "通过id获取后缀生成",
        "operationId" : "getGenerator",
        "produces" : [ "application/json;charset=UTF-8" ],
        "parameters" : [ {
          "name" : "id",
          "in" : "path",
          "description" : "后缀生成id",
          "required" : true,
          "type" : "integer",
          "format" : "int64"
        } ],
        "responses" : {
          "200" : {
            "description" : "successful request"
          },
          "500" : {
            "description" : "internal server error"
          }
        }
      },
      "put" : {
        "tags" : [ "后缀生成接口" ],
        "summary" : "更新后缀生成",
        "description" : "更新后缀生成信息",
        "operationId" : "updateGenerators",
        "produces" : [ "application/json;charset=UTF-8" ],
        "parameters" : [ {
          "name" : "id",
          "in" : "path",
          "description" : "后缀生成id",
          "required" : true,
          "type" : "integer",
          "format" : "int64"
        }, {
          "in" : "body",
          "name" : "body",
          "description" : "后缀生成信息",
          "required" : true,
          "schema" : {
            "$ref" : "#/definitions/GeneratorView"
          }
        } ],
        "responses" : {
          "200" : {
            "description" : "successful"
          },
          "404" : {
            "description" : "not found"
          },
          "409" : {
            "description" : "conflict"
          },
          "500" : {
            "description" : "internal Server Error"
          }
        }
      },
      "delete" : {
        "tags" : [ "后缀生成接口" ],
        "summary" : "删除后缀生成",
        "description" : "通过id删除后缀生成",
        "operationId" : "deleteGenerator",
        "produces" : [ "application/json;charset=UTF-8" ],
        "parameters" : [ {
          "name" : "id",
          "in" : "path",
          "description" : "后缀生成id",
          "required" : true,
          "type" : "integer",
          "format" : "int64"
        } ],
        "responses" : {
          "200" : {
            "description" : "successful request"
          },
          "500" : {
            "description" : "internal server error"
          }
        }
      }
    },
    "/api/v1/scholarships" : {
      "get" : {
        "tags" : [ "奖学金接口" ],
        "summary" : "获取奖学金列表",
        "description" : "通过查询条件获取奖学金列表",
        "operationId" : "getScholarships",
        "produces" : [ "application/json;charset=UTF-8" ],
        "parameters" : [ {
          "name" : "scholarshipLevel",
          "in" : "query",
          "description" : "奖学金等级",
          "required" : false,
          "type" : "integer",
          "format" : "int32"
        }, {
          "name" : "pageNumber",
          "in" : "query",
          "description" : "页数",
          "required" : false,
          "type" : "integer",
          "default" : 0,
          "format" : "int32"
        }, {
          "name" : "pageSize",
          "in" : "query",
          "description" : "每页加载量",
          "required" : false,
          "type" : "integer",
          "default" : 10,
          "format" : "int32"
        } ],
        "responses" : {
          "200" : {
            "description" : "successful request"
          },
          "500" : {
            "description" : "internal server error"
          }
        }
      },
      "post" : {
        "tags" : [ "奖学金接口" ],
        "summary" : "创建奖学金",
        "description" : "创建一个奖学金",
        "operationId" : "createScholarship",
        "produces" : [ "application/json;charset=UTF-8" ],
        "parameters" : [ {
          "in" : "body",
          "name" : "body",
          "description" : "奖学金",
          "required" : true,
          "schema" : {
            "$ref" : "#/definitions/ScholarshipView"
          }
        } ],
        "responses" : {
          "201" : {
            "description" : "successful operation",
            "headers" : {
              "location" : {
                "type" : "string",
                "description" : "URL of new created resource"
              }
            }
          },
          "409" : {
            "description" : "conflict"
          },
          "500" : {
            "description" : "internal server error"
          }
        }
      },
      "delete" : {
        "tags" : [ "奖学金接口" ],
        "summary" : "删除奖学金",
        "description" : "批量删除奖学金",
        "operationId" : "deleteScholarships",
        "produces" : [ "application/json;charset=UTF-8" ],
        "parameters" : [ {
          "in" : "body",
          "name" : "body",
          "description" : "奖学金ids，样例 - 1,2,3",
          "required" : true,
          "schema" : {
            "type" : "string"
          }
        } ],
        "responses" : {
          "200" : {
            "description" : "successful request"
          },
          "500" : {
            "description" : "internal server error"
          }
        }
      }
    },
    "/api/v1/scholarships/search" : {
      "get" : {
        "tags" : [ "奖学金接口" ],
        "summary" : "通过关键字搜索奖学金",
        "description" : "通过关键字搜索奖学金",
        "operationId" : "getScholarshipByKeyword",
        "produces" : [ "application/json;charset=UTF-8" ],
        "parameters" : [ {
          "name" : "keyword",
          "in" : "query",
          "description" : "关键字",
          "required" : true,
          "type" : "string"
        }, {
          "name" : "pageNumber",
          "in" : "query",
          "description" : "页数",
          "required" : false,
          "type" : "integer",
          "default" : 0,
          "format" : "int32"
        }, {
          "name" : "pageSize",
          "in" : "query",
          "description" : "每页加载量",
          "required" : false,
          "type" : "integer",
          "default" : 10,
          "format" : "int32"
        } ],
        "responses" : {
          "200" : {
            "description" : "successful request"
          },
          "500" : {
            "description" : "internal server error"
          }
        }
      }
    },
    "/api/v1/scholarships/{id}" : {
      "get" : {
        "tags" : [ "奖学金接口" ],
        "summary" : "获取单个奖学金",
        "description" : "通过id获取奖学金",
        "operationId" : "getScholarship",
        "produces" : [ "application/json;charset=UTF-8" ],
        "parameters" : [ {
          "name" : "id",
          "in" : "path",
          "description" : "奖学金id",
          "required" : true,
          "type" : "integer",
          "format" : "int64"
        } ],
        "responses" : {
          "200" : {
            "description" : "successful request"
          },
          "500" : {
            "description" : "internal server error"
          }
        }
      },
      "put" : {
        "tags" : [ "奖学金接口" ],
        "summary" : "更新奖学金",
        "description" : "更新奖学金信息",
        "operationId" : "updateScholarships",
        "produces" : [ "application/json;charset=UTF-8" ],
        "parameters" : [ {
          "name" : "id",
          "in" : "path",
          "description" : "奖学金id",
          "required" : true,
          "type" : "integer",
          "format" : "int64"
        }, {
          "in" : "body",
          "name" : "body",
          "description" : "奖学金信息",
          "required" : true,
          "schema" : {
            "$ref" : "#/definitions/ScholarshipView"
          }
        } ],
        "responses" : {
          "200" : {
            "description" : "successful"
          },
          "404" : {
            "description" : "not found"
          },
          "409" : {
            "description" : "conflict"
          },
          "500" : {
            "description" : "internal Server Error"
          }
        }
      },
      "delete" : {
        "tags" : [ "奖学金接口" ],
        "summary" : "删除奖学金",
        "description" : "通过id删除奖学金",
        "operationId" : "deleteScholarship",
        "produces" : [ "application/json;charset=UTF-8" ],
        "parameters" : [ {
          "name" : "id",
          "in" : "path",
          "description" : "奖学金id",
          "required" : true,
          "type" : "integer",
          "format" : "int64"
        } ],
        "responses" : {
          "200" : {
            "description" : "successful request"
          },
          "500" : {
            "description" : "internal server error"
          }
        }
      }
    },
    "/api/v1/scs" : {
      "get" : {
        "tags" : [ "成绩接口" ],
        "summary" : "获取成绩列表",
        "description" : "通过查询条件获取成绩列表",
        "operationId" : "getScs",
        "produces" : [ "application/json;charset=UTF-8" ],
        "parameters" : [ {
          "name" : "createTime",
          "in" : "query",
          "description" : "添加时间",
          "required" : false,
          "type" : "integer",
          "format" : "int64"
        }, {
          "name" : "updateTime",
          "in" : "query",
          "description" : "更新时间",
          "required" : false,
          "type" : "integer",
          "format" : "int64"
        }, {
          "name" : "studentNumber",
          "in" : "query",
          "description" : "学号",
          "required" : false,
          "type" : "string"
        }, {
          "name" : "studentName",
          "in" : "query",
          "description" : "学生姓名",
          "required" : false,
          "type" : "string"
        }, {
          "name" : "className",
          "in" : "query",
          "description" : "学生班级",
          "required" : false,
          "type" : "string"
        }, {
          "name" : "grade",
          "in" : "query",
          "description" : "年级",
          "required" : false,
          "type" : "string"
        }, {
          "name" : "courseNumber",
          "in" : "query",
          "description" : "课程号",
          "required" : false,
          "type" : "string"
        }, {
          "name" : "courseName",
          "in" : "query",
          "description" : "课程名称",
          "required" : false,
          "type" : "string"
        }, {
          "name" : "fraction",
          "in" : "query",
          "description" : "成绩",
          "required" : false,
          "type" : "integer",
          "format" : "int32"
        }, {
          "name" : "gradeRanking",
          "in" : "query",
          "description" : "全级排名",
          "required" : false,
          "type" : "integer",
          "format" : "int32"
        }, {
          "name" : "gradeRankingPercent",
          "in" : "query",
          "description" : "全级排名百分比",
          "required" : false,
          "type" : "number"
        }, {
          "name" : "classRanking",
          "in" : "query",
          "description" : "班级排名",
          "required" : false,
          "type" : "integer",
          "format" : "int32"
        }, {
          "name" : "classRankingPercent",
          "in" : "query",
          "description" : "班级排名百分比",
          "required" : false,
          "type" : "number"
        }, {
          "name" : "sort",
          "in" : "query",
          "description" : "排序方式",
          "required" : true,
          "type" : "string"
        }, {
          "name" : "sortDirection",
          "in" : "query",
          "description" : "升序或降序",
          "required" : true,
          "type" : "string"
        }, {
          "name" : "pageNumber",
          "in" : "query",
          "description" : "页数",
          "required" : false,
          "type" : "integer",
          "default" : 0,
          "format" : "int32"
        }, {
          "name" : "pageSize",
          "in" : "query",
          "description" : "每页加载量",
          "required" : false,
          "type" : "integer",
          "default" : 10,
          "format" : "int32"
        } ],
        "responses" : {
          "200" : {
            "description" : "successful request"
          },
          "500" : {
            "description" : "internal server error"
          }
        }
      },
      "post" : {
        "tags" : [ "成绩接口" ],
        "summary" : "创建成绩",
        "description" : "创建一个成绩",
        "operationId" : "createSc",
        "produces" : [ "application/json;charset=UTF-8" ],
        "parameters" : [ {
          "in" : "body",
          "name" : "body",
          "description" : "成绩",
          "required" : true,
          "schema" : {
            "$ref" : "#/definitions/ScView"
          }
        } ],
        "responses" : {
          "201" : {
            "description" : "successful operation",
            "headers" : {
              "location" : {
                "type" : "string",
                "description" : "URL of new created resource"
              }
            }
          },
          "409" : {
            "description" : "conflict"
          },
          "500" : {
            "description" : "internal server error"
          }
        }
      },
      "delete" : {
        "tags" : [ "成绩接口" ],
        "summary" : "删除成绩",
        "description" : "批量删除成绩",
        "operationId" : "deleteScs",
        "produces" : [ "application/json;charset=UTF-8" ],
        "parameters" : [ {
          "in" : "body",
          "name" : "body",
          "description" : "成绩ids，样例 - 1,2,3",
          "required" : true,
          "schema" : {
            "type" : "string"
          }
        } ],
        "responses" : {
          "200" : {
            "description" : "successful request"
          },
          "500" : {
            "description" : "internal server error"
          }
        }
      }
    },
    "/api/v1/scs/ranking/update" : {
      "put" : {
        "tags" : [ "成绩接口" ],
        "summary" : "更新成绩排行",
        "description" : "更新成绩信息",
        "operationId" : "updateScRankings",
        "produces" : [ "application/json;charset=UTF-8" ],
        "responses" : {
          "200" : {
            "description" : "successful"
          },
          "404" : {
            "description" : "not found"
          },
          "409" : {
            "description" : "conflict"
          },
          "500" : {
            "description" : "internal Server Error"
          }
        }
      }
    },
    "/api/v1/scs/search" : {
      "get" : {
        "tags" : [ "成绩接口" ],
        "summary" : "通过关键字搜索成绩",
        "description" : "通过关键字搜索成绩",
        "operationId" : "getScByKeyword",
        "produces" : [ "application/json;charset=UTF-8" ],
        "parameters" : [ {
          "name" : "keyword",
          "in" : "query",
          "description" : "关键字",
          "required" : true,
          "type" : "string"
        }, {
          "name" : "pageNumber",
          "in" : "query",
          "description" : "页数",
          "required" : false,
          "type" : "integer",
          "default" : 0,
          "format" : "int32"
        }, {
          "name" : "pageSize",
          "in" : "query",
          "description" : "每页加载量",
          "required" : false,
          "type" : "integer",
          "default" : 10,
          "format" : "int32"
        } ],
        "responses" : {
          "200" : {
            "description" : "successful request"
          },
          "500" : {
            "description" : "internal server error"
          }
        }
      }
    },
    "/api/v1/scs/{id}" : {
      "get" : {
        "tags" : [ "成绩接口" ],
        "summary" : "获取单个成绩",
        "description" : "通过id获取成绩",
        "operationId" : "getSc",
        "produces" : [ "application/json;charset=UTF-8" ],
        "parameters" : [ {
          "name" : "id",
          "in" : "path",
          "description" : "成绩id",
          "required" : true,
          "type" : "integer",
          "format" : "int64"
        } ],
        "responses" : {
          "200" : {
            "description" : "successful request"
          },
          "500" : {
            "description" : "internal server error"
          }
        }
      },
      "put" : {
        "tags" : [ "成绩接口" ],
        "summary" : "更新成绩",
        "description" : "更新成绩信息",
        "operationId" : "updateScs",
        "produces" : [ "application/json;charset=UTF-8" ],
        "parameters" : [ {
          "name" : "id",
          "in" : "path",
          "description" : "成绩id",
          "required" : true,
          "type" : "integer",
          "format" : "int64"
        }, {
          "in" : "body",
          "name" : "body",
          "description" : "成绩信息",
          "required" : true,
          "schema" : {
            "$ref" : "#/definitions/ScView"
          }
        } ],
        "responses" : {
          "200" : {
            "description" : "successful"
          },
          "404" : {
            "description" : "not found"
          },
          "409" : {
            "description" : "conflict"
          },
          "500" : {
            "description" : "internal Server Error"
          }
        }
      },
      "delete" : {
        "tags" : [ "成绩接口" ],
        "summary" : "删除成绩",
        "description" : "通过id删除成绩",
        "operationId" : "deleteSc",
        "produces" : [ "application/json;charset=UTF-8" ],
        "parameters" : [ {
          "name" : "id",
          "in" : "path",
          "description" : "成绩id",
          "required" : true,
          "type" : "integer",
          "format" : "int64"
        } ],
        "responses" : {
          "200" : {
            "description" : "successful request"
          },
          "500" : {
            "description" : "internal server error"
          }
        }
      }
    },
    "/api/v1/students" : {
      "get" : {
        "tags" : [ "学生接口" ],
        "summary" : "获取学生列表",
        "description" : "通过查询条件获取学生列表",
        "operationId" : "getStudents",
        "produces" : [ "application/json;charset=UTF-8" ],
        "parameters" : [ {
          "name" : "studentNumber",
          "in" : "query",
          "description" : "学号",
          "required" : false,
          "type" : "string"
        }, {
          "name" : "name",
          "in" : "query",
          "description" : "姓名",
          "required" : false,
          "type" : "string"
        }, {
          "name" : "gender",
          "in" : "query",
          "description" : "性别",
          "required" : false,
          "type" : "string"
        }, {
          "name" : "nativePlace",
          "in" : "query",
          "description" : "籍贯",
          "required" : false,
          "type" : "string"
        }, {
          "name" : "grade",
          "in" : "query",
          "description" : "年级",
          "required" : false,
          "type" : "string"
        }, {
          "name" : "className",
          "in" : "query",
          "description" : "班级名称",
          "required" : false,
          "type" : "string"
        }, {
          "name" : "scholarshipLevel",
          "in" : "query",
          "description" : "奖学金等级",
          "required" : false,
          "type" : "integer",
          "format" : "int32"
        }, {
          "name" : "isOutPut",
          "in" : "query",
          "description" : "是否导出",
          "required" : false,
          "type" : "integer",
          "default" : 0,
          "format" : "int32"
        }, {
          "name" : "pageNumber",
          "in" : "query",
          "description" : "页数",
          "required" : false,
          "type" : "integer",
          "default" : 0,
          "format" : "int32"
        }, {
          "name" : "pageSize",
          "in" : "query",
          "description" : "每页加载量",
          "required" : false,
          "type" : "integer",
          "default" : 10,
          "format" : "int32"
        } ],
        "responses" : {
          "200" : {
            "description" : "successful request"
          },
          "500" : {
            "description" : "internal server error"
          }
        }
      },
      "post" : {
        "tags" : [ "学生接口" ],
        "summary" : "创建学生",
        "description" : "创建一个学生",
        "operationId" : "createStudent",
        "produces" : [ "application/json;charset=UTF-8" ],
        "parameters" : [ {
          "in" : "body",
          "name" : "body",
          "description" : "学生",
          "required" : true,
          "schema" : {
            "$ref" : "#/definitions/StudentView"
          }
        } ],
        "responses" : {
          "201" : {
            "description" : "successful operation",
            "headers" : {
              "location" : {
                "type" : "string",
                "description" : "URL of new created resource"
              }
            }
          },
          "409" : {
            "description" : "conflict"
          },
          "500" : {
            "description" : "internal server error"
          }
        }
      },
      "delete" : {
        "tags" : [ "学生接口" ],
        "summary" : "删除学生",
        "description" : "批量删除学生",
        "operationId" : "deleteStudents",
        "produces" : [ "application/json;charset=UTF-8" ],
        "parameters" : [ {
          "in" : "body",
          "name" : "body",
          "description" : "学生ids，样例 - 1,2,3",
          "required" : true,
          "schema" : {
            "type" : "string"
          }
        } ],
        "responses" : {
          "200" : {
            "description" : "successful request"
          },
          "500" : {
            "description" : "internal server error"
          }
        }
      }
    },
    "/api/v1/students/classNames/all" : {
      "get" : {
        "tags" : [ "学生接口" ],
        "summary" : "获取班级列表",
        "description" : "获取班级列表",
        "operationId" : "getAllClassNames",
        "produces" : [ "application/json;charset=UTF-8" ],
        "responses" : {
          "200" : {
            "description" : "successful request"
          },
          "500" : {
            "description" : "internal server error"
          }
        }
      }
    },
    "/api/v1/students/genders/all" : {
      "get" : {
        "tags" : [ "学生接口" ],
        "summary" : "获取性别列表",
        "description" : "获取性别列表",
        "operationId" : "getAllGenders",
        "produces" : [ "application/json;charset=UTF-8" ],
        "responses" : {
          "200" : {
            "description" : "successful request"
          },
          "500" : {
            "description" : "internal server error"
          }
        }
      }
    },
    "/api/v1/students/grades/all" : {
      "get" : {
        "tags" : [ "学生接口" ],
        "summary" : "获取年级列表",
        "description" : "获取年级列表",
        "operationId" : "getAllGrades",
        "produces" : [ "application/json;charset=UTF-8" ],
        "responses" : {
          "200" : {
            "description" : "successful request"
          },
          "500" : {
            "description" : "internal server error"
          }
        }
      }
    },
    "/api/v1/students/scholarshipLevels/all" : {
      "get" : {
        "tags" : [ "学生接口" ],
        "summary" : "获取奖学金等级列表",
        "description" : "获取奖学金等级列表",
        "operationId" : "getAllScholarshipLevels",
        "produces" : [ "application/json;charset=UTF-8" ],
        "responses" : {
          "200" : {
            "description" : "successful request"
          },
          "500" : {
            "description" : "internal server error"
          }
        }
      }
    },
    "/api/v1/students/search" : {
      "get" : {
        "tags" : [ "学生接口" ],
        "summary" : "通过关键字搜索学生",
        "description" : "通过关键字搜索学生",
        "operationId" : "getStudentByKeyword",
        "produces" : [ "application/json;charset=UTF-8" ],
        "parameters" : [ {
          "name" : "keyword",
          "in" : "query",
          "description" : "关键字",
          "required" : true,
          "type" : "string"
        }, {
          "name" : "pageNumber",
          "in" : "query",
          "description" : "页数",
          "required" : false,
          "type" : "integer",
          "default" : 0,
          "format" : "int32"
        }, {
          "name" : "pageSize",
          "in" : "query",
          "description" : "每页加载量",
          "required" : false,
          "type" : "integer",
          "default" : 10,
          "format" : "int32"
        } ],
        "responses" : {
          "200" : {
            "description" : "successful request"
          },
          "500" : {
            "description" : "internal server error"
          }
        }
      }
    },
    "/api/v1/students/sumFraction/scholarship" : {
      "put" : {
        "tags" : [ "学生接口" ],
        "summary" : "更新学生",
        "description" : "更新学生信息",
        "operationId" : "updateStudentSumFractionAndScholarships",
        "produces" : [ "application/json;charset=UTF-8" ],
        "responses" : {
          "200" : {
            "description" : "successful"
          },
          "404" : {
            "description" : "not found"
          },
          "409" : {
            "description" : "conflict"
          },
          "500" : {
            "description" : "internal Server Error"
          }
        }
      }
    },
    "/api/v1/students/{id}" : {
      "get" : {
        "tags" : [ "学生接口" ],
        "summary" : "获取单个学生",
        "description" : "通过id获取学生",
        "operationId" : "getStudent",
        "produces" : [ "application/json;charset=UTF-8" ],
        "parameters" : [ {
          "name" : "id",
          "in" : "path",
          "description" : "学生id",
          "required" : true,
          "type" : "integer",
          "format" : "int64"
        } ],
        "responses" : {
          "200" : {
            "description" : "successful request"
          },
          "500" : {
            "description" : "internal server error"
          }
        }
      },
      "put" : {
        "tags" : [ "学生接口" ],
        "summary" : "更新学生",
        "description" : "更新学生信息",
        "operationId" : "updateStudents",
        "produces" : [ "application/json;charset=UTF-8" ],
        "parameters" : [ {
          "name" : "id",
          "in" : "path",
          "description" : "学生id",
          "required" : true,
          "type" : "integer",
          "format" : "int64"
        }, {
          "in" : "body",
          "name" : "body",
          "description" : "学生信息",
          "required" : true,
          "schema" : {
            "$ref" : "#/definitions/StudentView"
          }
        } ],
        "responses" : {
          "200" : {
            "description" : "successful"
          },
          "404" : {
            "description" : "not found"
          },
          "409" : {
            "description" : "conflict"
          },
          "500" : {
            "description" : "internal Server Error"
          }
        }
      },
      "delete" : {
        "tags" : [ "学生接口" ],
        "summary" : "删除学生",
        "description" : "通过id删除学生",
        "operationId" : "deleteStudent",
        "produces" : [ "application/json;charset=UTF-8" ],
        "parameters" : [ {
          "name" : "id",
          "in" : "path",
          "description" : "学生id",
          "required" : true,
          "type" : "integer",
          "format" : "int64"
        } ],
        "responses" : {
          "200" : {
            "description" : "successful request"
          },
          "500" : {
            "description" : "internal server error"
          }
        }
      }
    },
    "/api/v1/sysauthorities" : {
      "get" : {
        "tags" : [ "后台管理权限接口" ],
        "summary" : "获取后台管理权限列表",
        "description" : "通过查询条件获取后台管理权限列表",
        "operationId" : "getSysAuthoritys",
        "produces" : [ "application/json;charset=UTF-8" ],
        "parameters" : [ {
          "name" : "name",
          "in" : "query",
          "description" : "权限",
          "required" : false,
          "type" : "string"
        }, {
          "name" : "enabled",
          "in" : "query",
          "description" : "状态",
          "required" : false,
          "type" : "integer",
          "format" : "int32"
        }, {
          "name" : "pageNumber",
          "in" : "query",
          "description" : "页数",
          "required" : false,
          "type" : "integer",
          "default" : 0,
          "format" : "int32"
        }, {
          "name" : "pageSize",
          "in" : "query",
          "description" : "每页加载量",
          "required" : false,
          "type" : "integer",
          "default" : 10,
          "format" : "int32"
        } ],
        "responses" : {
          "200" : {
            "description" : "successful request"
          },
          "500" : {
            "description" : "internal server error"
          }
        }
      },
      "post" : {
        "tags" : [ "后台管理权限接口" ],
        "summary" : "创建后台管理权限",
        "description" : "创建一个后台管理权限",
        "operationId" : "createSysAuthority",
        "produces" : [ "application/json;charset=UTF-8" ],
        "parameters" : [ {
          "in" : "body",
          "name" : "body",
          "description" : "后台管理权限",
          "required" : true,
          "schema" : {
            "$ref" : "#/definitions/SysAuthorityView"
          }
        } ],
        "responses" : {
          "201" : {
            "description" : "successful operation",
            "headers" : {
              "location" : {
                "type" : "string",
                "description" : "URL of new created resource"
              }
            }
          },
          "409" : {
            "description" : "conflict"
          },
          "500" : {
            "description" : "internal server error"
          }
        }
      },
      "delete" : {
        "tags" : [ "后台管理权限接口" ],
        "summary" : "删除后台管理权限",
        "description" : "批量删除后台管理权限",
        "operationId" : "deleteSysAuthoritys",
        "produces" : [ "application/json;charset=UTF-8" ],
        "parameters" : [ {
          "in" : "body",
          "name" : "body",
          "description" : "后台管理权限ids",
          "required" : true,
          "schema" : {
            "type" : "string"
          }
        } ],
        "responses" : {
          "200" : {
            "description" : "successful request"
          },
          "500" : {
            "description" : "internal server error"
          }
        }
      }
    },
    "/api/v1/sysauthorities/{id}" : {
      "get" : {
        "tags" : [ "后台管理权限接口" ],
        "summary" : "获取后台管理权限",
        "description" : "通过id获取后台管理权限",
        "operationId" : "getSysAuthority",
        "produces" : [ "application/json;charset=UTF-8" ],
        "parameters" : [ {
          "name" : "id",
          "in" : "path",
          "description" : "后台管理权限id",
          "required" : true,
          "type" : "integer",
          "format" : "int64"
        } ],
        "responses" : {
          "200" : {
            "description" : "successful request"
          },
          "500" : {
            "description" : "internal server error"
          }
        }
      },
      "put" : {
        "tags" : [ "后台管理权限接口" ],
        "summary" : "更新后台管理权限",
        "description" : "更新后台管理权限信息",
        "operationId" : "updateSysAuthority",
        "produces" : [ "application/json;charset=UTF-8" ],
        "parameters" : [ {
          "name" : "id",
          "in" : "path",
          "description" : "权限id",
          "required" : true,
          "type" : "integer",
          "format" : "int64"
        }, {
          "in" : "body",
          "name" : "body",
          "description" : "权限信息",
          "required" : true,
          "schema" : {
            "$ref" : "#/definitions/SysAuthorityView"
          }
        } ],
        "responses" : {
          "200" : {
            "description" : "successful"
          },
          "404" : {
            "description" : "not found"
          },
          "409" : {
            "description" : "conflict"
          },
          "500" : {
            "description" : "internal Server Error"
          }
        }
      },
      "delete" : {
        "tags" : [ "后台管理权限接口" ],
        "summary" : "删除后台管理权限",
        "description" : "通过id删除后台管理权限",
        "operationId" : "deleteSysAuthority",
        "produces" : [ "application/json;charset=UTF-8" ],
        "parameters" : [ {
          "name" : "id",
          "in" : "path",
          "description" : "后台管理权限id",
          "required" : true,
          "type" : "integer",
          "format" : "int64"
        } ],
        "responses" : {
          "200" : {
            "description" : "successful request"
          },
          "500" : {
            "description" : "internal server error"
          }
        }
      }
    },
    "/api/v1/sysroles" : {
      "get" : {
        "tags" : [ "后台管理角色接口" ],
        "summary" : "获取后台管理角色列表",
        "description" : "通过查询条件获取后台管理角色列表",
        "operationId" : "getSysRoles",
        "produces" : [ "application/json;charset=UTF-8" ],
        "parameters" : [ {
          "name" : "chineseName",
          "in" : "query",
          "description" : "角色中文名",
          "required" : false,
          "type" : "string"
        }, {
          "name" : "enabled",
          "in" : "query",
          "description" : "状态",
          "required" : false,
          "type" : "integer",
          "format" : "int32"
        }, {
          "name" : "pageNumber",
          "in" : "query",
          "description" : "页数",
          "required" : false,
          "type" : "integer",
          "default" : 0,
          "format" : "int32"
        }, {
          "name" : "pageSize",
          "in" : "query",
          "description" : "每页加载量",
          "required" : false,
          "type" : "integer",
          "default" : 10,
          "format" : "int32"
        } ],
        "responses" : {
          "200" : {
            "description" : "successful request"
          },
          "500" : {
            "description" : "internal server error"
          }
        }
      },
      "post" : {
        "tags" : [ "后台管理角色接口" ],
        "summary" : "创建后台管理角色",
        "description" : "创建一个后台管理角色",
        "operationId" : "createSysRole",
        "produces" : [ "application/json;charset=UTF-8" ],
        "parameters" : [ {
          "in" : "body",
          "name" : "body",
          "description" : "后台管理角色",
          "required" : true,
          "schema" : {
            "$ref" : "#/definitions/SysRoleView"
          }
        } ],
        "responses" : {
          "201" : {
            "description" : "successful operation",
            "headers" : {
              "location" : {
                "type" : "string",
                "description" : "URL of new created resource"
              }
            }
          },
          "409" : {
            "description" : "conflict"
          },
          "500" : {
            "description" : "internal server error"
          }
        }
      },
      "delete" : {
        "tags" : [ "后台管理角色接口" ],
        "summary" : "批量删除后台管理角色",
        "description" : "批量删除后台管理角色",
        "operationId" : "deleteSysRoles",
        "produces" : [ "application/json;charset=UTF-8" ],
        "parameters" : [ {
          "in" : "body",
          "name" : "body",
          "description" : "后台管理角色ids",
          "required" : true,
          "schema" : {
            "type" : "string"
          }
        } ],
        "responses" : {
          "200" : {
            "description" : "successful request"
          },
          "500" : {
            "description" : "internal server error"
          }
        }
      }
    },
    "/api/v1/sysroles/{id}" : {
      "get" : {
        "tags" : [ "后台管理角色接口" ],
        "summary" : "获取后台管理角色",
        "description" : "通过id获取后台管理角色",
        "operationId" : "getSysRole",
        "produces" : [ "application/json;charset=UTF-8" ],
        "parameters" : [ {
          "name" : "id",
          "in" : "path",
          "description" : "后台管理角色id",
          "required" : true,
          "type" : "integer",
          "format" : "int64"
        } ],
        "responses" : {
          "200" : {
            "description" : "successful request"
          },
          "500" : {
            "description" : "internal server error"
          }
        }
      },
      "put" : {
        "tags" : [ "后台管理角色接口" ],
        "summary" : "更新后台管理角色",
        "description" : "更新后台管理角色信息",
        "operationId" : "updateRole",
        "produces" : [ "application/json;charset=UTF-8" ],
        "parameters" : [ {
          "name" : "id",
          "in" : "path",
          "description" : "角色id",
          "required" : true,
          "type" : "integer",
          "format" : "int64"
        }, {
          "in" : "body",
          "name" : "body",
          "description" : "角色信息",
          "required" : true,
          "schema" : {
            "$ref" : "#/definitions/SysRoleView"
          }
        } ],
        "responses" : {
          "200" : {
            "description" : "successful"
          },
          "404" : {
            "description" : "not found"
          },
          "409" : {
            "description" : "conflict"
          },
          "500" : {
            "description" : "internal Server Error"
          }
        }
      },
      "delete" : {
        "tags" : [ "后台管理角色接口" ],
        "summary" : "删除后台管理角色",
        "description" : "通过id删除后台管理角色",
        "operationId" : "deleteSysRole",
        "produces" : [ "application/json;charset=UTF-8" ],
        "parameters" : [ {
          "name" : "id",
          "in" : "path",
          "description" : "后台管理角色id",
          "required" : true,
          "type" : "integer",
          "format" : "int64"
        } ],
        "responses" : {
          "200" : {
            "description" : "successful request"
          },
          "500" : {
            "description" : "internal server error"
          }
        }
      }
    },
    "/api/v1/sysusers" : {
      "get" : {
        "tags" : [ "后台管理用户接口" ],
        "summary" : "获取后台管理用户列表",
        "description" : "通过查询条件获取后台管理用户列表",
        "operationId" : "getSysUsers",
        "produces" : [ "application/json;charset=UTF-8" ],
        "parameters" : [ {
          "name" : "userName",
          "in" : "query",
          "description" : "用户名",
          "required" : false,
          "type" : "string"
        }, {
          "name" : "enabled",
          "in" : "query",
          "description" : "状态",
          "required" : false,
          "type" : "integer",
          "format" : "int32"
        }, {
          "name" : "pageNumber",
          "in" : "query",
          "description" : "页数",
          "required" : false,
          "type" : "integer",
          "default" : 0,
          "format" : "int32"
        }, {
          "name" : "pageSize",
          "in" : "query",
          "description" : "每页加载量",
          "required" : false,
          "type" : "integer",
          "default" : 10,
          "format" : "int32"
        } ],
        "responses" : {
          "200" : {
            "description" : "successful request"
          },
          "500" : {
            "description" : "internal server error"
          }
        }
      },
      "post" : {
        "tags" : [ "后台管理用户接口" ],
        "summary" : "创建后台管理用户",
        "description" : "创建一个后台管理用户",
        "operationId" : "createSysUser",
        "produces" : [ "application/json;charset=UTF-8" ],
        "parameters" : [ {
          "in" : "body",
          "name" : "body",
          "description" : "后台管理用户",
          "required" : true,
          "schema" : {
            "$ref" : "#/definitions/SysUserView"
          }
        } ],
        "responses" : {
          "201" : {
            "description" : "successful operation",
            "headers" : {
              "location" : {
                "type" : "string",
                "description" : "URL of new created resource"
              }
            }
          },
          "409" : {
            "description" : "conflict"
          },
          "500" : {
            "description" : "internal server error"
          }
        }
      },
      "delete" : {
        "tags" : [ "后台管理用户接口" ],
        "summary" : "删除后台管理用户",
        "description" : "批量删除后台管理用户",
        "operationId" : "deleteSysUsers",
        "produces" : [ "application/json;charset=UTF-8" ],
        "parameters" : [ {
          "in" : "body",
          "name" : "body",
          "description" : "后台管理用户ids",
          "required" : true,
          "schema" : {
            "type" : "string"
          }
        } ],
        "responses" : {
          "200" : {
            "description" : "successful request"
          },
          "500" : {
            "description" : "internal server error"
          }
        }
      }
    },
    "/api/v1/sysusers/username/{username}" : {
      "get" : {
        "tags" : [ "后台管理用户接口" ],
        "summary" : "获取后台管理用户",
        "description" : "通过id获取后台管理用户",
        "operationId" : "getSysUserByUserName",
        "produces" : [ "application/json;charset=UTF-8" ],
        "parameters" : [ {
          "name" : "username",
          "in" : "path",
          "description" : "后台管理用户userName",
          "required" : true,
          "type" : "string"
        } ],
        "responses" : {
          "200" : {
            "description" : "successful request"
          },
          "500" : {
            "description" : "internal server error"
          }
        }
      }
    },
    "/api/v1/sysusers/{id}" : {
      "get" : {
        "tags" : [ "后台管理用户接口" ],
        "summary" : "获取后台管理用户",
        "description" : "通过id获取后台管理用户",
        "operationId" : "getSysUser",
        "produces" : [ "application/json;charset=UTF-8" ],
        "parameters" : [ {
          "name" : "id",
          "in" : "path",
          "description" : "后台管理用户id",
          "required" : true,
          "type" : "integer",
          "format" : "int64"
        } ],
        "responses" : {
          "200" : {
            "description" : "successful request"
          },
          "500" : {
            "description" : "internal server error"
          }
        }
      },
      "put" : {
        "tags" : [ "后台管理用户接口" ],
        "summary" : "更新后台管理用户",
        "description" : "更新后台管理用户信息",
        "operationId" : "updateUser",
        "produces" : [ "application/json;charset=UTF-8" ],
        "parameters" : [ {
          "name" : "id",
          "in" : "path",
          "description" : "用户id",
          "required" : true,
          "type" : "integer",
          "format" : "int64"
        }, {
          "in" : "body",
          "name" : "body",
          "description" : "用户信息",
          "required" : true,
          "schema" : {
            "$ref" : "#/definitions/SysUserView"
          }
        } ],
        "responses" : {
          "200" : {
            "description" : "successful"
          },
          "404" : {
            "description" : "not found"
          },
          "409" : {
            "description" : "conflict"
          },
          "500" : {
            "description" : "internal Server Error"
          }
        }
      },
      "delete" : {
        "tags" : [ "后台管理用户接口" ],
        "summary" : "删除后台管理用户",
        "description" : "通过id删除后台管理用户",
        "operationId" : "deleteSysUser",
        "produces" : [ "application/json;charset=UTF-8" ],
        "parameters" : [ {
          "name" : "id",
          "in" : "path",
          "description" : "后台管理用户id",
          "required" : true,
          "type" : "integer",
          "format" : "int64"
        } ],
        "responses" : {
          "200" : {
            "description" : "successful request"
          },
          "500" : {
            "description" : "internal server error"
          }
        }
      }
    },
    "/api/v1/upload/banner/pic" : {
      "post" : {
        "tags" : [ "上传模块" ],
        "summary" : "上传轮播图",
        "description" : "上传轮播图",
        "operationId" : "uploadBannerHeadImage",
        "produces" : [ "application/json;charset=UTF-8" ],
        "responses" : {
          "default" : {
            "description" : "successful operation"
          }
        }
      }
    }
  },
  "definitions" : {
    "AvgFractionView" : {
      "type" : "object",
      "properties" : {
        "id" : {
          "type" : "integer",
          "format" : "int64"
        },
        "courseNumber" : {
          "type" : "string"
        },
        "avgFraction" : {
          "type" : "number"
        }
      }
    },
    "ChangeView" : {
      "type" : "object",
      "properties" : {
        "id" : {
          "type" : "integer",
          "format" : "int64"
        },
        "changeName" : {
          "type" : "string"
        },
        "isChange" : {
          "type" : "string"
        }
      }
    },
    "ClassNameView" : {
      "type" : "object",
      "properties" : {
        "id" : {
          "type" : "integer",
          "format" : "int64"
        },
        "className" : {
          "type" : "string"
        },
        "grade" : {
          "type" : "string"
        }
      }
    },
    "CourseView" : {
      "type" : "object",
      "properties" : {
        "id" : {
          "type" : "integer",
          "format" : "int64"
        },
        "courseNumber" : {
          "type" : "string"
        },
        "name" : {
          "type" : "string"
        },
        "learnHours" : {
          "type" : "string"
        },
        "credit" : {
          "type" : "string"
        },
        "avgFraction" : {
          "type" : "number"
        },
        "preCourse" : {
          "type" : "integer",
          "format" : "int64"
        },
        "preCourseName" : {
          "type" : "string"
        }
      }
    },
    "GenderView" : {
      "type" : "object",
      "properties" : {
        "id" : {
          "type" : "integer",
          "format" : "int64"
        },
        "gender" : {
          "type" : "string"
        }
      }
    },
    "GeneratorView" : {
      "type" : "object",
      "properties" : {
        "id" : {
          "type" : "integer",
          "format" : "int64"
        },
        "name" : {
          "type" : "string"
        },
        "numberSuffix" : {
          "type" : "string"
        }
      }
    },
    "ScView" : {
      "type" : "object",
      "properties" : {
        "id" : {
          "type" : "integer",
          "format" : "int64"
        },
        "createTime" : {
          "type" : "integer",
          "format" : "int64"
        },
        "updateTime" : {
          "type" : "integer",
          "format" : "int64"
        },
        "studentNumber" : {
          "type" : "string"
        },
        "courseNumber" : {
          "type" : "string"
        },
        "fraction" : {
          "type" : "number"
        },
        "gradeRanking" : {
          "type" : "integer",
          "format" : "int32"
        },
        "gradeRankingPercent" : {
          "type" : "number"
        },
        "classRanking" : {
          "type" : "integer",
          "format" : "int32"
        },
        "classRankingPercent" : {
          "type" : "number"
        },
        "studentName" : {
          "type" : "string"
        },
        "className" : {
          "type" : "string"
        },
        "grade" : {
          "type" : "string"
        },
        "courseName" : {
          "type" : "string"
        }
      }
    },
    "ScholarshipView" : {
      "type" : "object",
      "properties" : {
        "id" : {
          "type" : "integer",
          "format" : "int64"
        },
        "scholarshipLevel" : {
          "type" : "integer",
          "format" : "int32"
        },
        "money" : {
          "type" : "number"
        },
        "number" : {
          "type" : "integer",
          "format" : "int32"
        }
      }
    },
    "StudentView" : {
      "type" : "object",
      "properties" : {
        "id" : {
          "type" : "integer",
          "format" : "int64"
        },
        "studentNumber" : {
          "type" : "string"
        },
        "name" : {
          "type" : "string"
        },
        "gender" : {
          "type" : "string"
        },
        "nativePlace" : {
          "type" : "string"
        },
        "grade" : {
          "type" : "string"
        },
        "className" : {
          "type" : "string"
        },
        "scholarshipLevel" : {
          "type" : "integer",
          "format" : "int32"
        },
        "sumFraction" : {
          "type" : "number"
        }
      }
    },
    "SysAuthority" : {
      "type" : "object",
      "properties" : {
        "id" : {
          "type" : "integer",
          "format" : "int64"
        },
        "hasAuthority" : {
          "type" : "boolean",
          "default" : false
        },
        "name" : {
          "type" : "string"
        },
        "description" : {
          "type" : "string"
        },
        "enabled" : {
          "type" : "integer",
          "format" : "int32"
        }
      }
    },
    "SysAuthorityView" : {
      "type" : "object",
      "properties" : {
        "id" : {
          "type" : "integer",
          "format" : "int64"
        },
        "hasAuthority" : {
          "type" : "boolean",
          "default" : false
        },
        "name" : {
          "type" : "string"
        },
        "description" : {
          "type" : "string"
        },
        "enabled" : {
          "type" : "integer",
          "format" : "int32"
        }
      }
    },
    "SysRole" : {
      "type" : "object",
      "properties" : {
        "id" : {
          "type" : "integer",
          "format" : "int64"
        },
        "hasRole" : {
          "type" : "boolean",
          "default" : false
        },
        "enabled" : {
          "type" : "integer",
          "format" : "int32"
        },
        "englishName" : {
          "type" : "string"
        },
        "chineseName" : {
          "type" : "string"
        },
        "description" : {
          "type" : "string"
        },
        "sysAuthorities" : {
          "type" : "array",
          "items" : {
            "$ref" : "#/definitions/SysAuthority"
          }
        }
      }
    },
    "SysRoleView" : {
      "type" : "object",
      "properties" : {
        "id" : {
          "type" : "integer",
          "format" : "int64"
        },
        "hasRole" : {
          "type" : "boolean",
          "default" : false
        },
        "enabled" : {
          "type" : "integer",
          "format" : "int32"
        },
        "englishName" : {
          "type" : "string"
        },
        "chineseName" : {
          "type" : "string"
        },
        "description" : {
          "type" : "string"
        },
        "sysAuthorities" : {
          "type" : "array",
          "items" : {
            "$ref" : "#/definitions/SysAuthority"
          }
        },
        "sysAuthoritiesWithRole" : {
          "type" : "array",
          "items" : {
            "$ref" : "#/definitions/SysAuthority"
          }
        }
      }
    },
    "SysUserView" : {
      "type" : "object",
      "properties" : {
        "id" : {
          "type" : "integer",
          "format" : "int64"
        },
        "userName" : {
          "type" : "string"
        },
        "password" : {
          "type" : "string"
        },
        "enabled" : {
          "type" : "integer",
          "format" : "int32"
        },
        "sysRole" : {
          "$ref" : "#/definitions/SysRole"
        }
      }
    }
  }
}